{
    "fluentMethods": true,
    "relationships": [
        {
            "relationshipName": "student",
            "otherEntityName": "student",
            "relationshipType": "many-to-one",
            "otherEntityField": "id"
        }
    ],
    "fields": [
        {
            "fieldName": "entitled",
            "fieldType": "String",
            "fieldValidateRules": [
                "required"
            ]
        },
        {
            "fieldName": "type",
            "fieldType": "String",
            "fieldValidateRules": [
                "required"
            ]
        },
        {
            "fieldName": "visible",
            "fieldType": "Boolean",
            "fieldValidateRules": [
                "required"
            ]
        },
        {
            "fieldName": "url",
            "fieldType": "String"
        }
    ],
    "changelogDate": "20180609180013",
    "entityTableName": "document",
    "dto": "mapstruct",
    "pagination": "no",
    "service": "serviceImpl",
    "jpaMetamodelFiltering": false
}